{"nodes": [{"id": "moon_workspace_config", "label": "Moon Workspace Config", "file_type": "document", "source_file": ".moon/workspace.yml", "source_location": null, "source_url": null, "captured_at": null, "author": null, "contributor": null}, {"id": "moon_workspace_project_api", "label": "Moon Project: api", "file_type": "concept", "source_file": ".moon/workspace.yml", "source_location": null, "source_url": null, "captured_at": null, "author": null, "contributor": null}, {"id": "moon_workspace_project_web", "label": "Moon Project: web", "file_type": "concept", "source_file": ".moon/workspace.yml", "source_location": null, "source_url": null, "captured_at": null, "author": null, "contributor": null}, {"id": "moon_workspace_project_tv", "label": "Moon Project: tv", "file_type": "concept", "source_file": ".moon/workspace.yml", "source_location": null, "source_url": null, "captured_at": null, "author": null, "contributor": null}, {"id": "moon_workspace_project_mobile", "label": "Moon Project: mobile", "file_type": "concept", "source_file": ".moon/workspace.yml", "source_location": null, "source_url": null, "captured_at": null, "author": null, "contributor": null}, {"id": "moon_workspace_project_desktop", "label": "Moon Project: desktop", "file_type": "concept", "source_file": ".moon/workspace.yml", "source_location": null, "source_url": null, "captured_at": null, "author": null, "contributor": null}, {"id": "moon_workspace_project_domain", "label": "Moon Project: domain", "file_type": "concept", "source_file": ".moon/workspace.yml", "source_location": null, "source_url": null, "captured_at": null, "author": null, "contributor": null}, {"id": "moon_workspace_project_api_client", "label": "Moon Project: api-client", "file_type": "concept", "source_file": ".moon/workspace.yml", "source_location": null, "source_url": null, "captured_at": null, "author": null, "contributor": null}, {"id": "moon_workspace_project_features", "label": "Moon Project: features", "file_type": "concept", "source_file": ".moon/workspace.yml", "source_location": null, "source_url": null, "captured_at": null, "author": null, "contributor": null}, {"id": "moon_workspace_project_ui", "label": "Moon Project: ui", "file_type": "concept", "source_file": ".moon/workspace.yml", "source_location": null, "source_url": null, "captured_at": null, "author": null, "contributor": null}, {"id": "moon_workspace_project_jellyfin", "label": "Moon Project: jellyfin", "file_type": "concept", "source_file": ".moon/workspace.yml", "source_location": null, "source_url": null, "captured_at": null, "author": null, "contributor": null}, {"id": "moon_workspace_project_player", "label": "Moon Project: player", "file_type": "concept", "source_file": ".moon/workspace.yml", "source_location": null, "source_url": null, "captured_at": null, "author": null, "contributor": null}], "edges": [{"source": "moon_workspace_config", "target": "moon_workspace_project_api", "relation": "references", "confidence": "EXTRACTED", "confidence_score": 1.0, "source_file": ".moon/workspace.yml", "source_location": null, "weight": 1.0}, {"source": "moon_workspace_config", "target": "moon_workspace_project_web", "relation": "references", "confidence": "EXTRACTED", "confidence_score": 1.0, "source_file": ".moon/workspace.yml", "source_location": null, "weight": 1.0}, {"source": "moon_workspace_config", "target": "moon_workspace_project_tv", "relation": "references", "confidence": "EXTRACTED", "confidence_score": 1.0, "source_file": ".moon/workspace.yml", "source_location": null, "weight": 1.0}, {"source": "moon_workspace_config", "target": "moon_workspace_project_mobile", "relation": "references", "confidence": "EXTRACTED", "confidence_score": 1.0, "source_file": ".moon/workspace.yml", "source_location": null, "weight": 1.0}, {"source": "moon_workspace_config", "target": "moon_workspace_project_desktop", "relation": "references", "confidence": "EXTRACTED", "confidence_score": 1.0, "source_file": ".moon/workspace.yml", "source_location": null, "weight": 1.0}, {"source": "moon_workspace_config", "target": "moon_workspace_project_domain", "relation": "references", "confidence": "EXTRACTED", "confidence_score": 1.0, "source_file": ".moon/workspace.yml", "source_location": null, "weight": 1.0}, {"source": "moon_workspace_config", "target": "moon_workspace_project_api_client", "relation": "references", "confidence": "EXTRACTED", "confidence_score": 1.0, "source_file": ".moon/workspace.yml", "source_location": null, "weight": 1.0}, {"source": "moon_workspace_config", "target": "moon_workspace_project_features", "relation": "references", "confidence": "EXTRACTED", "confidence_score": 1.0, "source_file": ".moon/workspace.yml", "source_location": null, "weight": 1.0}, {"source": "moon_workspace_config", "target": "moon_workspace_project_ui", "relation": "references", "confidence": "EXTRACTED", "confidence_score": 1.0, "source_file": ".moon/workspace.yml", "source_location": null, "weight": 1.0}, {"source": "moon_workspace_config", "target": "moon_workspace_project_jellyfin", "relation": "references", "confidence": "EXTRACTED", "confidence_score": 1.0, "source_file": ".moon/workspace.yml", "source_location": null, "weight": 1.0}, {"source": "moon_workspace_config", "target": "moon_workspace_project_player", "relation": "references", "confidence": "EXTRACTED", "confidence_score": 1.0, "source_file": ".moon/workspace.yml", "source_location": null, "weight": 1.0}, {"source": "moon_workspace_project_web", "target": "moon_workspace_config", "relation": "implements", "confidence": "EXTRACTED", "confidence_score": 1.0, "source_file": ".moon/workspace.yml", "source_location": null, "weight": 1.0}, {"source": "moon_workspace_project_api", "target": "apps_api_moon_project", "relation": "references", "confidence": "EXTRACTED", "confidence_score": 1.0, "source_file": ".moon/workspace.yml", "source_location": null, "weight": 1.0}, {"source": "moon_workspace_project_web", "target": "apps_web_moon_project", "relation": "references", "confidence": "EXTRACTED", "confidence_score": 1.0, "source_file": ".moon/workspace.yml", "source_location": null, "weight": 1.0}, {"source": "moon_workspace_project_tv", "target": "apps_tv_moon_project", "relation": "references", "confidence": "EXTRACTED", "confidence_score": 1.0, "source_file": ".moon/workspace.yml", "source_location": null, "weight": 1.0}, {"source": "moon_workspace_project_desktop", "target": "apps_desktop_moon_project", "relation": "references", "confidence": "EXTRACTED", "confidence_score": 1.0, "source_file": ".moon/workspace.yml", "source_location": null, "weight": 1.0}, {"source": "moon_workspace_project_mobile", "target": "apps_mobile_moon_project", "relation": "references", "confidence": "EXTRACTED", "confidence_score": 1.0, "source_file": ".moon/workspace.yml", "source_location": null, "weight": 1.0}, {"source": "moon_workspace_project_domain", "target": "packages_domain_moon_project", "relation": "references", "confidence": "EXTRACTED", "confidence_score": 1.0, "source_file": ".moon/workspace.yml", "source_location": null, "weight": 1.0}, {"source": "moon_workspace_project_api_client", "target": "packages_api_client_moon_project", "relation": "references", "confidence": "EXTRACTED", "confidence_score": 1.0, "source_file": ".moon/workspace.yml", "source_location": null, "weight": 1.0}, {"source": "moon_workspace_project_features", "target": "packages_features_moon_project", "relation": "references", "confidence": "EXTRACTED", "confidence_score": 1.0, "source_file": ".moon/workspace.yml", "source_location": null, "weight": 1.0}, {"source": "moon_workspace_project_ui", "target": "packages_ui_moon_project", "relation": "references", "confidence": "EXTRACTED", "confidence_score": 1.0, "source_file": ".moon/workspace.yml", "source_location": null, "weight": 1.0}, {"source": "moon_workspace_project_jellyfin", "target": "packages_jellyfin_moon_project", "relation": "references", "confidence": "EXTRACTED", "confidence_score": 1.0, "source_file": ".moon/workspace.yml", "source_location": null, "weight": 1.0}, {"source": "moon_workspace_project_player", "target": "packages_player_moon_project", "relation": "references", "confidence": "EXTRACTED", "confidence_score": 1.0, "source_file": ".moon/workspace.yml", "source_location": null, "weight": 1.0}], "hyperedges": []}