{"0": "seerr.ts", "1": "server.ts", "2": "jellyfinLibrary.ts", "3": "devDependencies", "4": "index.ts", "5": "Player", "6": "HomeScreen.tsx", "7": "AVPlay", "8": "NotificationsProvider.test.tsx", "9": "index.ts", "10": "playbackSession.ts", "11": "package.json", "12": "app.tsx", "13": "AVPlayPlayer", "14": "packages/features Moon Project C", "15": "index.ts", "16": "experience.tsx", "17": "ActionComponent", "18": "apps/tv Moon Project Config", "19": "index.ts", "20": "package.json", "21": "compilerOptions", "22": "App.tsx", "23": "web build task", "24": "index.ts", "25": "package.json", "26": "tizenDeviceProfile.ts", "27": "compilerOptions", "28": "Lolarr Monorepo (Moonrepo)", "29": "deviceProfile.ts", "30": "WebPlayer", "31": "package.json", "32": "scripts", "33": "Lolarr Slice 1: Fundament + Auth", "34": "package.json", "35": "AVPlayPlayer (Tizen native AVPla", "36": "packages/jellyfin Moon Project C", "37": "package.json", "38": "package.json", "39": "packages/domain", "40": "Docker Service: api", "41": "compilerOptions", "42": "package.json", "43": "PlayerControls.tsx", "44": "GET /api/home endpoint", "45": "Lolarr Slice 6: Seerr-Webhooks -", "46": "Moon Workspace Config", "47": "domain-schemas.test.ts", "48": "package.json", "49": "package.json", "50": "PlaybackSession orchestration", "51": "SeasonRequestPicker.tsx", "52": "dependencies", "53": "RequestList.tsx", "54": "dependencies", "55": "apps/api Moon Project Config", "56": "react.ts", "57": "devDependencies", "58": "devDependencies", "59": "apps/web Moon Project Config", "60": "scripts", "61": "EpisodeList.tsx", "62": "Norigin Spatial Navigation (SKIL", "63": "tsconfig.json", "64": "tsconfig.app.json", "65": "tsconfig.node.json", "66": "tsconfig.app.json", "67": "tsconfig.node.json", "68": "apps/api/src/modules/requests.ts", "69": "tsconfig.json", "70": "tsconfig.json", "71": "HomeScreenBadge.test.tsx", "72": "tsconfig.json", "73": "tsconfig.json", "74": "tsconfig.json", "75": "tsconfig.json", "76": "Lolarr Tizen App Favicon", "77": "tsconfig.json", "78": "tsconfig.json", "79": "vitest.config.ts", "80": "main.js", "81": "eslint.config.js", "82": "vitest.config.ts", "83": "vitest.config.ts", "84": "vitest.config.ts", "85": "vitest.config.ts"}